LICENSE
README.md
pyproject.toml
setup.cfg
setup.py
src/abci/__init__.py
src/abci/application.py
src/abci/server.py
src/abci/utils.py
src/example/__init__.py
src/example/counter.py
src/gogoproto/__init__.py
src/gogoproto/gogo_pb2.py
src/planetmint_abci.egg-info/PKG-INFO
src/planetmint_abci.egg-info/SOURCES.txt
src/planetmint_abci.egg-info/dependency_links.txt
src/planetmint_abci.egg-info/entry_points.txt
src/planetmint_abci.egg-info/requires.txt
src/planetmint_abci.egg-info/top_level.txt
src/tendermint/__init__.py
src/tendermint/abci/__init__.py
src/tendermint/abci/types_pb2.py
src/tendermint/crypto/__init__.py
src/tendermint/crypto/keys_pb2.py
src/tendermint/crypto/proof_pb2.py
src/tendermint/types/__init__.py
src/tendermint/types/params_pb2.py
src/tendermint/types/types_pb2.py
src/tendermint/types/validator_pb2.py
src/tendermint/version/__init__.py
src/tendermint/version/types_pb2.py
tests/test_protocol_handler.py
tests/test_wire.py