Metadata-Version: 2.1
Name: planetmint-abci
Version: 0.8.4
Summary: Python based ABCI Server for Tendermint
Home-page: https://github.com/eckelj/py-abci
Author: Dave Bryson
License: Apache 2.0
Project-URL: Source, https://github.com/eckelj/py-abci
Keywords: blockchain,tendermint,abci
Platform: unix
Platform: linux
Platform: osx
Platform: cygwin
Platform: win32
Classifier: Development Status :: 3 - Alpha
Classifier: Intended Audience :: Developers
Classifier: License :: OSI Approved :: Apache Software License
Classifier: Programming Language :: Python :: 3.9
Requires-Python: >=3.9
Provides-Extra: dev
License-File: LICENSE
